README.txt
setup.py
Chandler_ReportPlugin.egg-info/PKG-INFO
Chandler_ReportPlugin.egg-info/SOURCES.txt
Chandler_ReportPlugin.egg-info/dependency_links.txt
Chandler_ReportPlugin.egg-info/entry_points.txt
Chandler_ReportPlugin.egg-info/top_level.txt
reports/History.py
reports/ProgressReports.py
reports/ReportStamps.py
reports/__init__.py
reports/reportsentry_commands.py
reports/tests/TestReports.py
reports/tests/TestTimeParsing.py
reports/tests/__init__.py
