Metadata-Version: 1.0
Name: Chandler-ReportPlugin
Version: 0.1
Summary: Progress reports for Chandler
Home-page: UNKNOWN
Author: Vera Sheinman
Author-email: vera46@gmail.com
License: UNKNOWN
Platform: UNKNOWN
Classifier: Development Status :: 3 - Alpha
Classifier: Environment :: Plugins
Classifier: Framework :: Chandler
Classifier: Intended Audience :: Developers
Classifier: License :: OSI Approved :: Apache Software License
Classifier: Operating System :: OS Independent
Classifier: Programming Language :: Python
Classifier: Topic :: Office/Business :: Groupware
